ricochet_robots/__init__.py
ricochet_robots/__version__.py
ricochet_robots-0.0.0.dist-info/LICENSE
ricochet_robots-0.0.0.dist-info/METADATA
ricochet_robots-0.0.0.dist-info/WHEEL
ricochet_robots-0.0.0.dist-info/top_level.txt
ricochet_robots-0.0.0.dist-info/RECORD
