Metadata-Version: 2.1
Name: ricochet-robots
Version: 0.0.0
Summary: An implementation of Alex Randolph's game Ricochet Robots
Home-page: https://gitlab.com/mshepherd/ricochet-robots
Author: Markus Shepherd
Author-email: robots@recommend.games
License: MIT
Project-URL: Documentation, https://gitlab.com/mshepherd/ricochet-robots/blob/master/README.md
Project-URL: Source, https://gitlab.com/mshepherd/ricochet-robots
Project-URL: Tracker, https://gitlab.com/mshepherd/ricochet-robots/issues
Keywords: ricochet robots,game
Platform: UNKNOWN
Classifier: License :: OSI Approved :: MIT License
Classifier: Programming Language :: Python
Classifier: Programming Language :: Python :: 3.6
Classifier: Programming Language :: Python :: 3.7
Classifier: Programming Language :: Python :: 3.8
Requires-Python: >=3.6.0
